achs_mlops_quality/__init__.py
achs_mlops_quality/cli.py
achs_mlops_quality/models/__init__.py
achs_mlops_quality/models/library_checker.py
achs_mlops_quality/utils/__init__.py
mlops_quality_assurance-0.1.1.dist-info/METADATA
mlops_quality_assurance-0.1.1.dist-info/WHEEL
mlops_quality_assurance-0.1.1.dist-info/entry_points.txt
mlops_quality_assurance-0.1.1.dist-info/RECORD
