Metadata-Version: 2.4
Name: mlops-quality-assurance
Version: 0.1.1
Summary: Add your description here
Requires-Python: >=3.12
Requires-Dist: nbformat>=5.10.4
Requires-Dist: pytest>=8.4.1
Requires-Dist: typer>=0.16.0
